hazwaz/__init__.py
hazwaz/_version.py
hazwaz/command.py
hazwaz/mixins.py
hazwaz/py.typed
hazwaz/unittest.py
hazwaz-0.0.3.dist-info/METADATA
hazwaz-0.0.3.dist-info/WHEEL
hazwaz-0.0.3.dist-info/top_level.txt
hazwaz-0.0.3.dist-info/RECORD
