Metadata-Version: 2.1
Name: hazwaz
Version: 0.0.3
Summary: A command line scripts framework
Author-email: Elena ``of Valhalla'' Grandi <valhalla@trueelena.org>
License: AGPLv3+
Project-URL: Homepage, https://hazwaz.trueelena.org/
Project-URL: Documentation, https://hazwaz.trueelena.org/
Project-URL: Repository, https://git.sr.ht/~valhalla/hazwaz
Project-URL: Source, https://git.sr.ht/~valhalla/hazwaz
Project-URL: Issues, https://todo.sr.ht/~valhalla/hazwaz
Project-URL: Tracker, https://todo.sr.ht/~valhalla/hazwaz
Project-URL: Changelog, https://git.sr.ht/~valhalla/hazwaz/tree/master/item/CHANGELOG.rst
Keywords: cli
Classifier: Development Status :: 3 - Alpha
Classifier: Environment :: Console
Classifier: Intended Audience :: Developers
Classifier: License :: OSI Approved :: GNU Affero General Public License v3 or later (AGPLv3+)
Classifier: Operating System :: POSIX
Classifier: Programming Language :: Python :: 3 :: Only
Classifier: Programming Language :: Python :: 3.9
Classifier: Programming Language :: Python :: 3.10
Classifier: Topic :: Software Development :: Libraries :: Python Modules
Classifier: Topic :: Software Development :: User Interfaces
Requires-Python: >=3.9
